cubicweb_massmailing/__init__.py
cubicweb_massmailing/__pkginfo__.py
cubicweb_massmailing/views.py
cubicweb_massmailing/data/cubicweb.mailform.css
cubicweb_massmailing/i18n/en.po
cubicweb_massmailing/i18n/es.po
cubicweb_massmailing/i18n/fr.po
cubicweb_massmailing/migration/postcreate.py
cubicweb_massmailing-1.0.0.dist-info/METADATA
cubicweb_massmailing-1.0.0.dist-info/WHEEL
cubicweb_massmailing-1.0.0.dist-info/entry_points.txt
cubicweb_massmailing-1.0.0.dist-info/top_level.txt
cubicweb_massmailing-1.0.0.dist-info/RECORD
