Metadata-Version: 2.1
Name: cubicweb-massmailing
Version: 1.0.0
Summary: Mass mailing handling: send mail to entities adaptable to IEmailable
Home-page: http://www.cubicweb.org/project/cubicweb-massmailing
Author: LOGILAB S.A. (Paris, FRANCE)
Author-email: contact@logilab.fr
License: LGPL
Classifier: Environment :: Web Environment
Classifier: Framework :: CubicWeb
Classifier: Programming Language :: Python :: 3
Classifier: Programming Language :: JavaScript
Requires-Dist: cubicweb (<5.0.0,>=4.0.0)
Requires-Dist: cubicweb-web (<2.0.0,>=1.0.0)
